[
  {
    "campaign": "C1",
    "episode": 25,
    "episode_position_pct": 0.0772,
    "speaker": "MATT",
    "event_type": "init_event",
    "raw_text": "We're now rolling for initiative.",
    "preceding_context_chars": 1214,
    "extractor_version": "encounter_cadence_v1_1",
    "extracted_at": "2026-05-05T19:53:52Z",
    "trigger_turn_number": 146,
    "trigger_category": "npc_turns_hostile",
    "is_fresh_encounter": true,
    "wave_subtype": null,
    "player_action_caused": false,
    "narration_buildup_chars": 595,
    "preceding_turns": [
      {
        "speaker": "LIAM",
        "text": "Well, here's the thing you need to know about Uriel. And I take a step back.",
        "turn_number": 121
      },
      {
        "speaker": "MATT",
        "text": "Into him?",
        "turn_number": 122
      },
      {
        "speaker": "LIAM",
        "text": "No! Away.",
        "turn_number": 123
      },
      {
        "speaker": "MATT",
        "text": "He's between you and the door.",
        "turn_number": 124
      },
      {
        "speaker": "LIAM",
        "text": "Well, does he hold me if I turn? Well, I just said that, right? Here's the thing about Uriel.",
        "turn_number": 125
      },
      {
        "speaker": "MATT",
        "text": "As you go to move away, his arms that are on your shoulder, tighten, flex, and hold you in place.",
        "turn_number": 126
      },
      {
        "speaker": "LIAM",
        "text": "Oh, you don't want to know? Okay, I'll just save that for later.",
        "turn_number": 127
      },
      {
        "speaker": "SAM",
        "text": "Roll for coy.",
        "turn_number": 128
      },
      {
        "speaker": "LIAM",
        "text": "Roll for what, Matt?",
        "turn_number": 129
      },
      {
        "speaker": "MATT",
        "text": "Since I don't know what you're going to say, I'm going to say persuasion for this. Because I don't know if it's a deception or not.",
        "turn_number": 130
      },
      {
        "speaker": "TRAVIS",
        "text": "Is the power out of the DM's hands for a moment?",
        "turn_number": 131
      },
      {
        "speaker": "LIAM",
        "text": "Oh, I'm going to use my last Luck of the day!",
        "turn_number": 132
      },
      {
        "speaker": "TRAVIS",
        "text": "The last one?",
        "turn_number": 133
      },
      {
        "speaker": "LIAM",
        "text": "Last Luck of the day.",
        "turn_number": 134
      },
      {
        "speaker": "LAURA",
        "text": "Oh my god.",
        "turn_number": 135
      },
      {
        "speaker": "LIAM",
        "text": "Okay, this is persuasion? That's 17.",
        "turn_number": 136
      },
      {
        "speaker": "TRAVIS",
        "text": "That was a big die.",
        "turn_number": 137
      },
      {
        "speaker": "LIAM",
        "text": "You could give me a-- never mind.",
        "turn_number": 138
      },
      {
        "speaker": "MATT",
        "text": "You want an inspiration?",
        "turn_number": 139
      },
      {
        "speaker": "LIAM",
        "text": "Huh? No.",
        "turn_number": 140
      },
      {
        "speaker": "MATT",
        "text": "(laughs) What are you asking for? What are you begging from the DM?",
        "turn_number": 141
      },
      {
        "speaker": "LIAM",
        "text": "Yeah, no, that's why I said never mind.",
        "turn_number": 142
      },
      {
        "speaker": "TRAVIS",
        "text": "Is it begging or is it praying, at this point?",
        "turn_number": 143
      },
      {
        "speaker": "MATT",
        "text": "No, I'll give inspiration when you've goddamn earned it. As you say that looking at them with this coy look of information about Uriel, they both chuckle in unison. (chuckles) \"Shall we?\" And she gives a nod and goes, \"I think we shall.\"",
        "turn_number": 144
      },
      {
        "speaker": "LIAM",
        "text": "Can I roll for initiative?",
        "turn_number": 145
      }
    ]
  },
  {
    "campaign": "C1",
    "episode": 25,
    "episode_position_pct": 0.1196,
    "speaker": "MATT",
    "event_type": "init_event",
    "raw_text": "The door is currently closed, but you're in eagle form, so you're going to be doing like eagles do. I'll say, you're about there because you were a little bit ahead of them. Those are the two guards right there. At this point now, as this is happening, I need you guys to go ahead and roll initiative.",
    "preceding_context_chars": 1230,
    "extractor_version": "encounter_cadence_v1_1",
    "extracted_at": "2026-05-05T19:53:52Z",
    "trigger_turn_number": 226,
    "trigger_category": "npc_turns_hostile",
    "is_fresh_encounter": true,
    "wave_subtype": null,
    "player_action_caused": false,
    "narration_buildup_chars": 690,
    "preceding_turns": [
      {
        "speaker": "LAURA",
        "text": "I guess running towards the Briarwoods' room.",
        "turn_number": 214
      },
      {
        "speaker": "MATT",
        "text": "Where you saw them leave? You head up the stairway, following behind where you saw Keyleth and Tiberius rush off to. Are you following the rest of them?",
        "turn_number": 215
      },
      {
        "speaker": "SAM",
        "text": "Yeah. I put my mug down and I start little leg waddling towards them. As I go, I'm going to send a message. I use Message to-- who's the guy who likes us?",
        "turn_number": 216
      },
      {
        "speaker": "LIAM",
        "text": "My name is Vax.",
        "turn_number": 217
      },
      {
        "speaker": "SAM",
        "text": "No, not him. Sylas? No, not Sylas! Seeker Asum?",
        "turn_number": 218
      },
      {
        "speaker": "MATT",
        "text": "Seeker Asum, with Message? I believe the person has to be within visual range. Wait, no. You can cast through solid objects if you're familiar with the target and nobody on the barrier. It's 120 foot, though. You don't know how far he is. You could give it a shot.",
        "turn_number": 219
      },
      {
        "speaker": "SAM",
        "text": "Okay, I say, something's gone awry. We may need you right away.",
        "turn_number": 220
      },
      {
        "speaker": "MATT",
        "text": "The message is delivered out into the space. Hopefully, it found its recipient.",
        "turn_number": 221
      },
      {
        "speaker": "LAURA",
        "text": "As I'm running towards the Briarwoods' room, I start shouting Uriel! and grab a servant and say, go find Uriel. Tell him there's enemies within the gates, in the castle. Now!",
        "turn_number": 222
      },
      {
        "speaker": "MATT",
        "text": "\"Yes, Lady Vex. Right away.\" Runs off. You guys coast up the stairs. Right as you reach the top of the hallway over here, you can see there are two guards that are currently standing at the door.",
        "turn_number": 223
      },
      {
        "speaker": "TRAVIS",
        "text": "I stay at the front door.",
        "turn_number": 224
      },
      {
        "speaker": "MARISHA",
        "text": "Is the door open?",
        "turn_number": 225
      }
    ]
  },
  {
    "campaign": "C1",
    "episode": 25,
    "episode_position_pct": 0.1365,
    "speaker": "MATT",
    "event_type": "init_event",
    "raw_text": "I'm going to have people who haven't rolled initiative yet, go ahead and roll initiative so I can put you on the timing chart here. Grog?",
    "preceding_context_chars": 1460,
    "extractor_version": "encounter_cadence_v1_1",
    "extracted_at": "2026-05-05T19:53:52Z",
    "trigger_turn_number": 258,
    "trigger_category": "player_action_escalation",
    "is_fresh_encounter": true,
    "wave_subtype": null,
    "player_action_caused": true,
    "narration_buildup_chars": 636,
    "preceding_turns": [
      {
        "speaker": "MARISHA",
        "text": "Well, he's not in the room. He's in the front yard, at this point. So we are heading to the room.",
        "turn_number": 250
      },
      {
        "speaker": "LIAM",
        "text": "Wait. As that happens, and as my consciousness fades away, I don't say anything, but here's what I think in a split-second. I think of my friends that I have spent so much time with. I think of Keyleth, beautiful, walking under the trees. I think of my twin sister as a young girl, folding up linens with our mother. I think of my sister as an adolescent in lessons, smarter than me. I think of the woman she grew into. Hiking over many, many, many miles together. My best friend. My best friend, Vex'ahlia. And before I can think no more, I say a prayer to Sarenrae to watch over my friends and keep them safe.",
        "turn_number": 251
      },
      {
        "speaker": "MATT",
        "text": "Go ahead and make a wisdom saving throw.",
        "turn_number": 252
      },
      {
        "speaker": "LIAM",
        "text": "Eight.",
        "turn_number": 253
      },
      {
        "speaker": "MATT",
        "text": "With that thought cast out, the darkness swallows your vision and unconsciousness takes you into the cold, wet grass on the floor of the courtyard surrounding the palace. A small shiver runs down your spine, Vex: a feeling you haven't felt before. A feeling of sudden and immediate sourceless dread, and in that instant you know that there is almost no time.",
        "turn_number": 254
      },
      {
        "speaker": "LAURA",
        "text": "Can I use Hunter's Mark and sense where Lady Briarwood is at that moment?",
        "turn_number": 255
      },
      {
        "speaker": "MATT",
        "text": "Yeah, she is actually at this point, beyond the palace walls. You can sense and knowing the palace walls. You were expecting a second floor, it's that direction but just outside the walls of the palace. And you guys just got your weapons.",
        "turn_number": 256
      },
      {
        "speaker": "LAURA",
        "text": "I take off running in that direction.",
        "turn_number": 257
      }
    ]
  },
  {
    "campaign": "C1",
    "episode": 25,
    "episode_position_pct": 0.4995,
    "speaker": "MATT",
    "event_type": "init_event",
    "raw_text": "Hold on. As you've guys are just turning the corner. You can see now Lord Briarwood stands up and is trying to compose himself, ruffles himself up angrily, looking at his damaged circumstance. Lady Briarwood's against his shoulder and she goes, (clicks tongue) \"Well, (sighs) at the very least, I think you should come visit us sometime, Percy. You're always welcome back home. It'd be nice of you to visit your family once in a while.\" Roll initiative. Just you. As you were the first action to take.",
    "preceding_context_chars": 1483,
    "extractor_version": "encounter_cadence_v1_1",
    "extracted_at": "2026-05-05T19:53:52Z",
    "trigger_turn_number": 944,
    "trigger_category": "player_action_escalation",
    "is_fresh_encounter": true,
    "wave_subtype": null,
    "player_action_caused": true,
    "narration_buildup_chars": 1181,
    "preceding_turns": [
      {
        "speaker": "MARISHA",
        "text": "I still have my Sleet Storm up. It's a concentration spell. I'm going to move it over there.",
        "turn_number": 928
      },
      {
        "speaker": "MATT",
        "text": "Can you just shift it over there?",
        "turn_number": 929
      },
      {
        "speaker": "MARISHA",
        "text": "Yeah. It's a concentration spell. It lasts a minute.",
        "turn_number": 930
      },
      {
        "speaker": "MATT",
        "text": "Oh well no, it's concentration to keep it in the area.",
        "turn_number": 931
      },
      {
        "speaker": "MARISHA",
        "text": "Well, then I cast it again.",
        "turn_number": 932
      },
      {
        "speaker": "MATT",
        "text": "So you're casting Sleet Storm again. What's the range on it?",
        "turn_number": 933
      },
      {
        "speaker": "MARISHA",
        "text": "150 feet.",
        "turn_number": 934
      },
      {
        "speaker": "MATT",
        "text": "150 feet. The sleet storm lands down. The cobblestone becomes sleek; the carriage begins rocking back and forth. However, it does manage to keep on its course, currently; it does not get knocked prone. It's hard to knock a carriage prone, but it is sliding out of the way.",
        "turn_number": 935
      },
      {
        "speaker": "TALIESIN",
        "text": "Is that a disadvantage because it only has three wheels?",
        "turn_number": 936
      },
      {
        "speaker": "MATT",
        "text": "Good call, actually.",
        "turn_number": 937
      },
      {
        "speaker": "MARISHA",
        "text": "And it's rough terrain?",
        "turn_number": 938
      },
      {
        "speaker": "MATT",
        "text": "That is a two. (cheering)",
        "turn_number": 939
      },
      {
        "speaker": "MATT",
        "text": "At this point, the carriage (crash) slams onto the side of the ground and skids (creaking) to a halt in the middle of the ice, the sleet still spackling down as you guys all turn the corner now; as you approach. The gates have closed (slamming) as the guards have slammed it, listening to Grog on the far side. The door pops open on the side of the carriage. Tiberius, as you've made your way back around and you're at the front now, (panting) and you can see now, about 60 feet in front of you the carriage is overturned in the middle of this sleet storm, on the ground.",
        "turn_number": 940
      },
      {
        "speaker": "ORION",
        "text": "Where is it?",
        "turn_number": 941
      },
      {
        "speaker": "MATT",
        "text": "From a visual standpoint, you're about 60 to 70 feet from the front of this. The doors slam open and you can see Lord and Lady Briarwood step out.",
        "turn_number": 942
      },
      {
        "speaker": "LAURA",
        "text": "Can I shoot my exploding arrow?",
        "turn_number": 943
      }
    ]
  },
  {
    "campaign": "C1",
    "episode": 25,
    "episode_position_pct": 0.7317,
    "speaker": "MATT",
    "event_type": "init_event",
    "raw_text": "You are, yes. And we're going to go ahead and have you guys roll initiative.",
    "preceding_context_chars": 1470,
    "extractor_version": "encounter_cadence_v1_1",
    "extracted_at": "2026-05-05T19:53:52Z",
    "trigger_turn_number": 1383,
    "trigger_category": "interruption",
    "is_fresh_encounter": true,
    "wave_subtype": null,
    "player_action_caused": false,
    "narration_buildup_chars": 957,
    "preceding_turns": [
      {
        "speaker": "ORION",
        "text": "Yes.",
        "turn_number": 1365
      },
      {
        "speaker": "LAURA",
        "text": "You're guarded against scrying in your room?",
        "turn_number": 1366
      },
      {
        "speaker": "ORION",
        "text": "Guards against scrying? Yes, of course!",
        "turn_number": 1367
      },
      {
        "speaker": "SAM",
        "text": "Is that true?",
        "turn_number": 1368
      },
      {
        "speaker": "LAURA",
        "text": "Against scrying.",
        "turn_number": 1369
      },
      {
        "speaker": "MARISHA",
        "text": "I'm pretty sure we would have to have an enchantment on our keep that would guard against scrying.",
        "turn_number": 1370
      },
      {
        "speaker": "MATT",
        "text": "As you guys are having this discussion, a voice rings out behind you and says, \"Don't worry. It's not going to help you.\"",
        "turn_number": 1371
      },
      {
        "speaker": "TRAVIS",
        "text": "Is that little shitty Mr. Missing One Hand?",
        "turn_number": 1372
      },
      {
        "speaker": "MATT",
        "text": "No. You turn around and look, and you can see a gentleman standing there about 25 feet away from you. You see dark brown and black studded leather armor with a cloak over one shoulder. Standing straight, with a grin. Deep dark red skin, burning yellow eyes and jet black, slicked hair between two horns that jut back. A tiefling stands there, looking forward, with two individuals flanking from side to side that are slowly stepping--",
        "turn_number": 1373
      },
      {
        "speaker": "ORION",
        "text": "I don't know what they do, but I'm raising my arm up. Who goes there? Who are you? I've had a really bad day.",
        "turn_number": 1374
      },
      {
        "speaker": "MATT",
        "text": "The tiefling, the male tiefling, steps up forward and says, \"I've no quarrel with any of you. We've been scouring this city for a fugitive for a number of weeks. And as luck would have it, you guys happened to smoke her out of her hole.\"",
        "turn_number": 1375
      },
      {
        "speaker": "MARISHA",
        "text": "I go ahead and crack my staff on the ground and cast Anti-life Shell.",
        "turn_number": 1376
      },
      {
        "speaker": "MATT",
        "text": "Okay.",
        "turn_number": 1377
      },
      {
        "speaker": "LIAM",
        "text": "And are they at the door?",
        "turn_number": 1378
      },
      {
        "speaker": "MATT",
        "text": "You guys are walking from the outside of the wall to your keep.",
        "turn_number": 1379
      },
      {
        "speaker": "LIAM",
        "text": "Where are they?",
        "turn_number": 1380
      },
      {
        "speaker": "MATT",
        "text": "Right now? They are coming from Emon. You guys are in this in-between section between your keep--",
        "turn_number": 1381
      },
      {
        "speaker": "LIAM",
        "text": "We're outdoors? We've left the temple?",
        "turn_number": 1382
      }
    ]
  }
]