[
  {
    "campaign": "C2",
    "episode": 20,
    "episode_position_pct": 0.3667,
    "speaker": "MATT",
    "event_type": "init_event",
    "raw_text": "Jester, you make your way up over to that side. The rest of you are currently trying to catch up on that end of the table. That being the case, I need everyone to roll initiative.",
    "preceding_context_chars": 1345,
    "extractor_version": "encounter_cadence_v1_2",
    "extracted_at": "2026-05-06T04:33:58Z",
    "trigger_turn_number": 967,
    "trigger_category": "interruption",
    "is_fresh_encounter": true,
    "wave_subtype": null,
    "player_action_caused": false,
    "narration_buildup_chars": 501,
    "nearest_prior_trigger_turn_distance": null,
    "preceding_turns": [
      {
        "speaker": "LAURA",
        "text": "Don't worry, we'll save you! There's a thing, and it's trapped and there's the reptile thing that's going to eat it!",
        "turn_number": 932
      },
      {
        "speaker": "TRAVIS",
        "text": "Where? Which direction?",
        "turn_number": 933
      },
      {
        "speaker": "LAURA",
        "text": "Over there. I point and I start climbing over and try to get to it.",
        "turn_number": 934
      },
      {
        "speaker": "LIAM",
        "text": "Do we even see her anymore?",
        "turn_number": 935
      },
      {
        "speaker": "MATT",
        "text": "You see her in the tree, you don't see what she's looking at and pointing at. She climbs down the tree and begins running in that direction.",
        "turn_number": 936
      },
      {
        "speaker": "LAURA",
        "text": "It's about 100 feet away. Don't worry.",
        "turn_number": 937
      },
      {
        "speaker": "SAM",
        "text": "Don't worry? What?",
        "turn_number": 938
      },
      {
        "speaker": "TALIESIN",
        "text": "What?",
        "turn_number": 939
      },
      {
        "speaker": "MATT",
        "text": "She's ran off.",
        "turn_number": 940
      },
      {
        "speaker": "SAM",
        "text": "Shit.",
        "turn_number": 941
      },
      {
        "speaker": "TRAVIS",
        "text": "Fuck. I'll run off after her.",
        "turn_number": 942
      },
      {
        "speaker": "ASHLEY",
        "text": "Same.",
        "turn_number": 943
      },
      {
        "speaker": "MARISHA",
        "text": "What are we saving?",
        "turn_number": 944
      },
      {
        "speaker": "SAM",
        "text": "I don't know. Right now, we're saving Jester.",
        "turn_number": 945
      },
      {
        "speaker": "MARISHA",
        "text": "I'm still on a horse, yeah? I'm on a horse.",
        "turn_number": 946
      },
      {
        "speaker": "MATT",
        "text": "You are, yeah. You're staying on your horse to get there?",
        "turn_number": 947
      },
      {
        "speaker": "MARISHA",
        "text": "Yeah, I'm staying on my horse!",
        "turn_number": 948
      },
      {
        "speaker": "TRAVIS",
        "text": "You're going to hard tax your horse?",
        "turn_number": 949
      },
      {
        "speaker": "MARISHA",
        "text": "(galloping) How cool is that?",
        "turn_number": 950
      },
      {
        "speaker": "MATT",
        "text": "Well, it's cool for the first minute before it goes (mud slurping).",
        "turn_number": 951
      },
      {
        "speaker": "LAURA",
        "text": "Guiding Bolt is an attack thing, so I have to roll to attack.",
        "turn_number": 952
      },
      {
        "speaker": "MATT",
        "text": "Oh, got you. Roll to attack.",
        "turn_number": 953
      },
      {
        "speaker": "LAURA",
        "text": "Oh, no. Okay, it definitely hits. It's plus seven, 16, 23.",
        "turn_number": 954
      },
      {
        "speaker": "MATT",
        "text": "Yeah, that hits. All right, cool. So timeline worked out.",
        "turn_number": 955
      },
      {
        "speaker": "LAURA",
        "text": "Yay!",
        "turn_number": 956
      },
      {
        "speaker": "MATT",
        "text": "As you approach, this is the visual from the side that you see.",
        "turn_number": 957
      },
      {
        "speaker": "TRAVIS",
        "text": "Yay, map time!",
        "turn_number": 958
      },
      {
        "speaker": "LAURA",
        "text": "I'm so glad we checked out what it was.",
        "turn_number": 959
      },
      {
        "speaker": "TRAVIS",
        "text": "(beatboxing)",
        "turn_number": 960
      },
      {
        "speaker": "LAURA",
        "text": "Oh shit!",
        "turn_number": 961
      },
      {
        "speaker": "SAM",
        "text": "So many trees.",
        "turn_number": 962
      },
      {
        "speaker": "LAURA",
        "text": "Oh my god, look at all these trees.",
        "turn_number": 963
      },
      {
        "speaker": "TRAVIS",
        "text": "Damn.",
        "turn_number": 964
      },
      {
        "speaker": "MATT",
        "text": "This here is the gator that you see making its way there. It is very large.",
        "turn_number": 965
      },
      {
        "speaker": "LAURA",
        "text": "Oh no, it's really big. Look at that teeny little bird guy.",
        "turn_number": 966
      }
    ]
  }
]